Level1/stopwatch_V3.v
//stopwatch_V3.v

module stopwatch (
  input clk, reset, Start, Stop, Clear, Countdown,
  output reg [3:0] Minutes, Tens_Seconds, Ones_Seconds, Tenths_Seconds
  );
  
     reg running,nice_D;
	always@(posedge clk)
	begin
		if(Start) running <=1;
		if(Stop) running <=0;
	end
	
	always@(Countdown)
	begin
		if(~Countdown) nice_D <=0;
		else nice_D <=1;
	end
	
	always@(posedge clk) begin
			if (reset) begin
				Minutes 		<= 4'd0;
				Tens_Seconds	<= 4'd0;
				Ones_Seconds	<= 4'd0;
				Tenths_Seconds	<= 4'd0;
			end 
		end
	
	always@(posedge clk)begin
		if (running && ~nice_D)begin
			if (Tenths_Seconds == 4'd9) begin // Check if tenths_seconds reaches 9
				Tenths_Seconds <= 0;		  // Reset to 0 on reaching 9
				Ones_Seconds <= Ones_Seconds + 1;
			end else begin
				Tenths_Seconds <= Tenths_Seconds + 1; // Increment tenths_seconds 
			end
			if (Ones_Seconds == 4'd9 && Tenths_Seconds == 4'd9) begin
					Ones_Seconds <= 0;
					Tens_Seconds <= Tens_Seconds +1;
				end
			if (Tens_Seconds == 4'd5 && Ones_Seconds == 4'd9 && Tenths_Seconds == 4'd9 ) begin
				Tens_Seconds <= 0;
				Minutes <= Minutes +1;
				end
			if (Minutes == 4'd9 && Tens_Seconds == 4'd5 && Ones_Seconds == 4'd9 && Tenths_Seconds == 4'd9) begin
				Minutes <= 0;
				end
		end
		// Count down logic
		if (running && nice_D)begin
			if (Tenths_Seconds == 4'd0) begin
				Tenths_Seconds <= 4'd9;
				Ones_Seconds <= Ones_Seconds - 1;
				end else begin
					Tenths_Seconds <= Tenths_Seconds -1;
					end
			if(Ones_Seconds == 4'd0 && Tenths_Seconds == 4'b0) begin
				Ones_Seconds <= 4'd9;
				Tens_Seconds <= Tens_Seconds - 1;
				end
			if (Tens_Seconds == 4'd0 && Ones_Seconds == 4'd0 && Tenths_Seconds == 4'd0 ) begin
				Tens_Seconds <= 4'd5;
				Minutes <= Minutes -1;
				end
			if (Minutes == 4'd0 && Tens_Seconds == 4'd0 && Ones_Seconds == 4'd0 && Tenths_Seconds == 4'd0) begin
				Minutes <= 4'd9;
				end
			end
	end

endmodule

Level1/tb_stopwatch_V3.v
//tb_Stopwatch_V3.v

// Testbench for Stopwatch Counter
`timescale 10ms/1ms
module stopwatch_tb;

  // Inputs
  reg clk;
  reg reset;
  reg Start;
  reg Stop;
  reg Countdown;

  // Outputs
  wire [3:0] Tenths_Seconds;
  wire [3:0] Ones_Seconds;
  wire [3:0] Tens_Seconds;
  wire [3:0] Minutes;


  // DUT (Device Under Test) - Your Stopwatch Counter Module
  stopwatch dut (
    .clk(clk),
    .reset(reset),
	.Start(Start),
	.Stop(Stop),
	.Countdown(Countdown),
    .Tenths_Seconds(Tenths_Seconds),
    .Ones_Seconds(Ones_Seconds),
    .Tens_Seconds(Tens_Seconds),
    .Minutes(Minutes)
  );

  // Clock generation
  initial begin
    clk = 1'b0;
    forever #5 clk = ~clk; // Generate clock with 50ns period (20MHz)
  end

  // Stimulus (reset for 100ns, then run for 1 minute)
  initial begin
  $dumpfile("dump.vcd");
  $dumpvars(0,stopwatch_tb);
    reset = 1'b1;
	Start = 1'b1;
	Countdown = 1'b0;
    #10; //
    reset = 1'b0;
	Start = 1'b0;
	#1000
	Stop = 1'b1;
	#100;
	Stop = 1'b0;
	#2000;
	Start = 1'b1;
    #10; //
    Start = 1'b0;
	#5000;
	Countdown = 1'b1;
	#80000;
	Countdown = 1'b0;
    #11004; // Wait for 1 minute (60 seconds * 1 billion ns/second)
    $finish;
  end



endmodule

Level1/dump.vcd
$date
	Tue Apr 30 10:34:11 2024
$end
$version
	Icarus Verilog
$end
$timescale
	1ms
$end
$scope module stopwatch_tb $end
$var wire 4 ! Tenths_Seconds [3:0] $end
$var wire 4 " Tens_Seconds [3:0] $end
$var wire 4 # Ones_Seconds [3:0] $end
$var wire 4 $ Minutes [3:0] $end
$var reg 1 % Countdown $end
$var reg 1 & Start $end
$var reg 1 ' Stop $end
$var reg 1 ( clk $end
$var reg 1 ) reset $end
$scope module dut $end
$var wire 1 * Clear $end
$var wire 1 % Countdown $end
$var wire 1 & Start $end
$var wire 1 ' Stop $end
$var wire 1 ( clk $end
$var wire 1 ) reset $end
$var reg 4 + Minutes [3:0] $end
$var reg 4 , Ones_Seconds [3:0] $end
$var reg 4 - Tens_Seconds [3:0] $end
$var reg 4 . Tenths_Seconds [3:0] $end
$var reg 1 / nice_D $end
$var reg 1 0 running $end
$upscope $end
$upscope $end
$enddefinitions $end
$comment Show the parameter values. $end
$dumpall
$end
#0
$dumpvars
10
0/
bx .
bx -
bx ,
bx +
z*
1)
0(
x'
1&
0%
bx $
bx #
bx "
bx !
$end
#50
b0 !
b0 .
b0 #
b0 ,
b0 "
b0 -
b0 $
b0 +
1(
#100
0(
0&
0)
#150
b1 !
b1 .
1(
#200
0(
#250
b10 !
b10 .
1(
#300
0(
#350
b11 !
b11 .
1(
#400
0(
#450
b100 !
b100 .
1(
#500
0(
#550
b101 !
b101 .
1(
#600
0(
#650
b110 !
b110 .
1(
#700
0(
#750
b111 !
b111 .
1(
#800
0(
#850
b1000 !
b1000 .
1(
#900
0(
#950
b1001 !
b1001 .
1(
#1000
0(
#1050
b1 #
b1 ,
b0 !
b0 .
1(
#1100
0(
#1150
b1 !
b1 .
1(
#1200
0(
#1250
b10 !
b10 .
1(
#1300
0(
#1350
b11 !
b11 .
1(
#1400
0(
#1450
b100 !
b100 .
1(
#1500
0(
#1550
b101 !
b101 .
1(
#1600
0(
#1650
b110 !
b110 .
1(
#1700
0(
#1750
b111 !
b111 .
1(
#1800
0(
#1850
b1000 !
b1000 .
1(
#1900
0(
#1950
b1001 !
b1001 .
1(
#2000
0(
#2050
b10 #
b10 ,
b0 !
b0 .
1(
#2100
0(
#2150
b1 !
b1 .
1(
#2200
0(
#2250
b10 !
b10 .
1(
#2300
0(
#2350
b11 !
b11 .
1(
#2400
0(
#2450
b100 !
b100 .
1(
#2500
0(
#2550
b101 !
b101 .
1(
#2600
0(
#2650
b110 !
b110 .
1(
#2700
0(
#2750
b111 !
b111 .
1(
#2800
0(
#2850
b1000 !
b1000 .
1(
#2900
0(
#2950
b1001 !
b1001 .
1(
#3000
0(
#3050
b11 #
b11 ,
b0 !
b0 .
1(
#3100
0(
#3150
b1 !
b1 .
1(
#3200
0(
#3250
b10 !
b10 .
1(
#3300
0(
#3350
b11 !
b11 .
1(
#3400
0(
#3450
b100 !
b100 .
1(
#3500
0(
#3550
b101 !
b101 .
1(
#3600
0(
#3650
b110 !
b110 .
1(
#3700
0(
#3750
b111 !
b111 .
1(
#3800
0(
#3850
b1000 !
b1000 .
1(
#3900
0(
#3950
b1001 !
b1001 .
1(
#4000
0(
#4050
b100 #
b100 ,
b0 !
b0 .
1(
#4100
0(
#4150
b1 !
b1 .
1(
#4200
0(
#4250
b10 !
b10 .
1(
#4300
0(
#4350
b11 !
b11 .
1(
#4400
0(
#4450
b100 !
b100 .
1(
#4500
0(
#4550
b101 !
b101 .
1(
#4600
0(
#4650
b110 !
b110 .
1(
#4700
0(
#4750
b111 !
b111 .
1(
#4800
0(
#4850
b1000 !
b1000 .
1(
#4900
0(
#4950
b1001 !
b1001 .
1(
#5000
0(
#5050
b101 #
b101 ,
b0 !
b0 .
1(
#5100
0(
#5150
b1 !
b1 .
1(
#5200
0(
#5250
b10 !
b10 .
1(
#5300
0(
#5350
b11 !
b11 .
1(
#5400
0(
#5450
b100 !
b100 .
1(
#5500
0(
#5550
b101 !
b101 .
1(
#5600
0(
#5650
b110 !
b110 .
1(
#5700
0(
#5750
b111 !
b111 .
1(
#5800
0(
#5850
b1000 !
b1000 .
1(
#5900
0(
#5950
b1001 !
b1001 .
1(
#6000
0(
#6050
b110 #
b110 ,
b0 !
b0 .
1(
#6100
0(
#6150
b1 !
b1 .
1(
#6200
0(
#6250
b10 !
b10 .
1(
#6300
0(
#6350
b11 !
b11 .
1(
#6400
0(
#6450
b100 !
b100 .
1(
#6500
0(
#6550
b101 !
b101 .
1(
#6600
0(
#6650
b110 !
b110 .
1(
#6700
0(
#6750
b111 !
b111 .
1(
#6800
0(
#6850
b1000 !
b1000 .
1(
#6900
0(
#6950
b1001 !
b1001 .
1(
#7000
0(
#7050
b111 #
b111 ,
b0 !
b0 .
1(
#7100
0(
#7150
b1 !
b1 .
1(
#7200
0(
#7250
b10 !
b10 .
1(
#7300
0(
#7350
b11 !
b11 .
1(
#7400
0(
#7450
b100 !
b100 .
1(
#7500
0(
#7550
b101 !
b101 .
1(
#7600
0(
#7650
b110 !
b110 .
1(
#7700
0(
#7750
b111 !
b111 .
1(
#7800
0(
#7850
b1000 !
b1000 .
1(
#7900
0(
#7950
b1001 !
b1001 .
1(
#8000
0(
#8050
b1000 #
b1000 ,
b0 !
b0 .
1(
#8100
0(
#8150
b1 !
b1 .
1(
#8200
0(
#8250
b10 !
b10 .
1(
#8300
0(
#8350
b11 !
b11 .
1(
#8400
0(
#8450
b100 !
b100 .
1(
#8500
0(
#8550
b101 !
b101 .
1(
#8600
0(
#8650
b110 !
b110 .
1(
#8700
0(
#8750
b111 !
b111 .
1(
#8800
0(
#8850
b1000 !
b1000 .
1(
#8900
0(
#8950
b1001 !
b1001 .
1(
#9000
0(
#9050
b1001 #
b1001 ,
b0 !
b0 .
1(
#9100
0(
#9150
b1 !
b1 .
1(
#9200
0(
#9250
b10 !
b10 .
1(
#9300
0(
#9350
b11 !
b11 .
1(
#9400
0(
#9450
b100 !
b100 .
1(
#9500
0(
#9550
b101 !
b101 .
1(
#9600
0(
#9650
b110 !
b110 .
1(
#9700
0(
#9750
b111 !
b111 .
1(
#9800
0(
#9850
b1000 !
b1000 .
1(
#9900
0(
#9950
b1001 !
b1001 .
1(
#10000
0(
#10050
b1 "
b1 -
b0 #
b0 ,
b0 !
b0 .
1(
#10100
00
0(
1'
#10150
1(
#10200
0(
#10250
1(
#10300
0(
#10350
1(
#10400
0(
#10450
1(
#10500
0(
#10550
1(
#10600
0(
#10650
1(
#10700
0(
#10750
1(
#10800
0(
#10850
1(
#10900
0(
#10950
1(
#11000
0(
#11050
1(
#11100
0(
0'
